[ {
  "team_id" : 7291,
  "team_name" : "Odisha",
  "lineup" : [ {
    "player_id" : 8150,
    "player_name" : "Francisco Javier Hernández González",
    "player_nickname" : "Javi Hernández",
    "jersey_number" : 10,
    "country" : {
      "id" : 214,
      "name" : "Spain"
    },
    "cards" : [ ],
    "positions" : [ {
      "position_id" : 23,
      "position" : "Center Forward",
      "from" : "00:00",
      "to" : "45:00",
      "from_period" : 1,
      "to_period" : 2,
      "start_reason" : "Starting XI",
      "end_reason" : "Substitution - Off (Tactical)"
    } ]
  }, {
    "player_id" : 8584,
    "player_name" : "Jonathas Cristian de Jesus",
    "player_nickname" : "Jonathas",
    "jersey_number" : 9,
    "country" : {
      "id" : 31,
      "name" : "Brazil"
    },
    "cards" : [ ],
    "positions" : [ {
      "position_id" : 5,
      "position" : "Left Center Back",
      "from" : "45:00",
      "to" : "45:09",
      "from_period" : 2,
      "to_period" : 2,
      "start_reason" : "Substitution - On (Tactical)",
      "end_reason" : "Tactical Shift"
    }, {
      "position_id" : 23,
      "position" : "Center Forward",
      "from" : "45:09",
      "to" : null,
      "from_period" : 2,
      "to_period" : null,
      "start_reason" : "Tactical Shift",
      "end_reason" : "Final Whistle"
    } ]
  }, {
    "player_id" : 24268,
    "player_name" : "Ariday Cabrera Suárez",
    "player_nickname" : "Ariday Cabrera",
    "jersey_number" : 7,
    "country" : {
      "id" : 214,
      "name" : "Spain"
    },
    "cards" : [ ],
    "positions" : [ {
      "position_id" : 23,
      "position" : "Center Forward",
      "from" : "45:00",
      "to" : "45:09",
      "from_period" : 2,
      "to_period" : 2,
      "start_reason" : "Substitution - On (Tactical)",
      "end_reason" : "Tactical Shift"
    }, {
      "position_id" : 21,
      "position" : "Left Wing",
      "from" : "45:09",
      "to" : null,
      "from_period" : 2,
      "to_period" : null,
      "start_reason" : "Tactical Shift",
      "end_reason" : "Final Whistle"
    } ]
  }, {
    "player_id" : 24860,
    "player_name" : "Héctor Rodas Ramírez",
    "player_nickname" : "Héctor Rodas",
    "jersey_number" : 4,
    "country" : {
      "id" : 214,
      "name" : "Spain"
    },
    "cards" : [ ],
    "positions" : [ {
      "position_id" : 3,
      "position" : "Right Center Back",
      "from" : "00:00",
      "to" : null,
      "from_period" : 1,
      "to_period" : null,
      "start_reason" : "Starting XI",
      "end_reason" : "Final Whistle"
    } ]
  }, {
    "player_id" : 100434,
    "player_name" : "Liridon Krasniqi",
    "player_nickname" : null,
    "jersey_number" : 92,
    "country" : {
      "id" : 138,
      "name" : "Malaysia"
    },
    "cards" : [ ],
    "positions" : [ {
      "position_id" : 19,
      "position" : "Center Attacking Midfield",
      "from" : "00:00",
      "to" : "45:09",
      "from_period" : 1,
      "to_period" : 2,
      "start_reason" : "Starting XI",
      "end_reason" : "Tactical Shift"
    }, {
      "position_id" : 15,
      "position" : "Left Center Midfield",
      "from" : "45:09",
      "to" : null,
      "from_period" : 2,
      "to_period" : null,
      "start_reason" : "Tactical Shift",
      "end_reason" : "Final Whistle"
    } ]
  }, {
    "player_id" : 124769,
    "player_name" : "Vinit Rai Chamling",
    "player_nickname" : null,
    "jersey_number" : 16,
    "country" : {
      "id" : 105,
      "name" : "India"
    },
    "cards" : [ ],
    "positions" : [ {
      "position_id" : 13,
      "position" : "Right Center Midfield",
      "from" : "00:00",
      "to" : null,
      "from_period" : 1,
      "to_period" : null,
      "start_reason" : "Starting XI",
      "end_reason" : "Final Whistle"
    } ]
  }, {
    "player_id" : 124784,
    "player_name" : "Kamaljit Singh",
    "player_nickname" : null,
    "jersey_number" : 30,
    "country" : {
      "id" : 105,
      "name" : "India"
    },
    "cards" : [ ],
    "positions" : [ {
      "position_id" : 1,
      "position" : "Goalkeeper",
      "from" : "00:00",
      "to" : null,
      "from_period" : 1,
      "to_period" : null,
      "start_reason" : "Starting XI",
      "end_reason" : "Final Whistle"
    } ]
  }, {
    "player_id" : 162201,
    "player_name" : "Víctor Mongil Adeva",
    "player_nickname" : "Víctor Mongil",
    "jersey_number" : 3,
    "country" : {
      "id" : 214,
      "name" : "Spain"
    },
    "cards" : [ ],
    "positions" : [ {
      "position_id" : 5,
      "position" : "Left Center Back",
      "from" : "00:00",
      "to" : "45:00",
      "from_period" : 1,
      "to_period" : 2,
      "start_reason" : "Starting XI",
      "end_reason" : "Substitution - Off (Tactical)"
    } ]
  }, {
    "player_id" : 162212,
    "player_name" : "Lalruatthara Lalruatthara",
    "player_nickname" : null,
    "jersey_number" : 39,
    "country" : {
      "id" : 105,
      "name" : "India"
    },
    "cards" : [ ],
    "positions" : [ {
      "position_id" : 6,
      "position" : "Left Back",
      "from" : "00:00",
      "to" : null,
      "from_period" : 1,
      "to_period" : null,
      "start_reason" : "Starting XI",
      "end_reason" : "Final Whistle"
    } ]
  }, {
    "player_id" : 162213,
    "player_name" : "Hendry Antonay",
    "player_nickname" : null,
    "jersey_number" : 22,
    "country" : {
      "id" : 105,
      "name" : "India"
    },
    "cards" : [ ],
    "positions" : [ {
      "position_id" : 2,
      "position" : "Right Back",
      "from" : "00:00",
      "to" : null,
      "from_period" : 1,
      "to_period" : null,
      "start_reason" : "Starting XI",
      "end_reason" : "Final Whistle"
    } ]
  }, {
    "player_id" : 162214,
    "player_name" : "Jerry Mawihmingthanga",
    "player_nickname" : null,
    "jersey_number" : 17,
    "country" : {
      "id" : 105,
      "name" : "India"
    },
    "cards" : [ ],
    "positions" : [ {
      "position_id" : 17,
      "position" : "Right Wing",
      "from" : "00:00",
      "to" : "75:06",
      "from_period" : 1,
      "to_period" : 2,
      "start_reason" : "Starting XI",
      "end_reason" : "Substitution - Off (Tactical)"
    } ]
  }, {
    "player_id" : 162215,
    "player_name" : "Nandhakumar Sekar",
    "player_nickname" : null,
    "jersey_number" : 11,
    "country" : {
      "id" : 105,
      "name" : "India"
    },
    "cards" : [ ],
    "positions" : [ {
      "position_id" : 21,
      "position" : "Left Wing",
      "from" : "00:00",
      "to" : "33:40",
      "from_period" : 1,
      "to_period" : 1,
      "start_reason" : "Starting XI",
      "end_reason" : "Substitution - Off (Injury)"
    } ]
  }, {
    "player_id" : 162216,
    "player_name" : "Moirangthem Thoiba Singh",
    "player_nickname" : null,
    "jersey_number" : 24,
    "country" : {
      "id" : 105,
      "name" : "India"
    },
    "cards" : [ ],
    "positions" : [ {
      "position_id" : 15,
      "position" : "Left Center Midfield",
      "from" : "00:00",
      "to" : "45:00",
      "from_period" : 1,
      "to_period" : 2,
      "start_reason" : "Starting XI",
      "end_reason" : "Substitution - Off (Tactical)"
    } ]
  }, {
    "player_id" : 162217,
    "player_name" : "Isak Vanlalruatfela",
    "player_nickname" : null,
    "jersey_number" : 19,
    "country" : {
      "id" : 105,
      "name" : "India"
    },
    "cards" : [ ],
    "positions" : [ {
      "position_id" : 21,
      "position" : "Left Wing",
      "from" : "33:40",
      "to" : "45:09",
      "from_period" : 1,
      "to_period" : 2,
      "start_reason" : "Substitution - On (Injury)",
      "end_reason" : "Tactical Shift"
    }, {
      "position_id" : 19,
      "position" : "Center Attacking Midfield",
      "from" : "45:09",
      "to" : null,
      "from_period" : 2,
      "to_period" : null,
      "start_reason" : "Tactical Shift",
      "end_reason" : "Final Whistle"
    } ]
  }, {
    "player_id" : 162218,
    "player_name" : "Lalhrezuala Sailung",
    "player_nickname" : null,
    "jersey_number" : 2,
    "country" : {
      "id" : 105,
      "name" : "India"
    },
    "cards" : [ ],
    "positions" : [ ]
  }, {
    "player_id" : 162219,
    "player_name" : "Isaac Vanmalsawma Chhakchhuak",
    "player_nickname" : null,
    "jersey_number" : 48,
    "country" : {
      "id" : 105,
      "name" : "India"
    },
    "cards" : [ ],
    "positions" : [ {
      "position_id" : 17,
      "position" : "Right Wing",
      "from" : "75:06",
      "to" : null,
      "from_period" : 2,
      "to_period" : null,
      "start_reason" : "Substitution - On (Tactical)",
      "end_reason" : "Final Whistle"
    } ]
  }, {
    "player_id" : 162220,
    "player_name" : "Arshdeep Singh Saini",
    "player_nickname" : null,
    "jersey_number" : 1,
    "country" : {
      "id" : 105,
      "name" : "India"
    },
    "cards" : [ ],
    "positions" : [ ]
  }, {
    "player_id" : 162221,
    "player_name" : "Daniel Lalhlimpuia",
    "player_nickname" : null,
    "jersey_number" : 14,
    "country" : {
      "id" : 105,
      "name" : "India"
    },
    "cards" : [ ],
    "positions" : [ ]
  }, {
    "player_id" : 162222,
    "player_name" : "Gaurav Bora",
    "player_nickname" : null,
    "jersey_number" : 13,
    "country" : {
      "id" : 105,
      "name" : "India"
    },
    "cards" : [ ],
    "positions" : [ {
      "position_id" : 15,
      "position" : "Left Center Midfield",
      "from" : "45:00",
      "to" : "45:09",
      "from_period" : 2,
      "to_period" : 2,
      "start_reason" : "Substitution - On (Tactical)",
      "end_reason" : "Tactical Shift"
    }, {
      "position_id" : 5,
      "position" : "Left Center Back",
      "from" : "45:09",
      "to" : null,
      "from_period" : 2,
      "to_period" : null,
      "start_reason" : "Tactical Shift",
      "end_reason" : "Final Whistle"
    } ]
  }, {
    "player_id" : 167382,
    "player_name" : "Nikhil Raj Murugesh Kumar",
    "player_nickname" : null,
    "jersey_number" : 21,
    "country" : {
      "id" : 105,
      "name" : "India"
    },
    "cards" : [ ],
    "positions" : [ ]
  } ]
}, {
  "team_id" : 7286,
  "team_name" : "East Bengal",
  "lineup" : [ {
    "player_id" : 32945,
    "player_name" : "Franjo Prce",
    "player_nickname" : null,
    "jersey_number" : 71,
    "country" : {
      "id" : 56,
      "name" : "Croatia"
    },
    "cards" : [ ],
    "positions" : [ {
      "position_id" : 5,
      "position" : "Left Center Back",
      "from" : "00:00",
      "to" : "58:27",
      "from_period" : 1,
      "to_period" : 2,
      "start_reason" : "Starting XI",
      "end_reason" : "Substitution - Off (Tactical)"
    } ]
  }, {
    "player_id" : 33638,
    "player_name" : "Tomislav Mrčela",
    "player_nickname" : null,
    "jersey_number" : 4,
    "country" : {
      "id" : 14,
      "name" : "Australia"
    },
    "cards" : [ ],
    "positions" : [ {
      "position_id" : 5,
      "position" : "Left Center Back",
      "from" : "58:27",
      "to" : null,
      "from_period" : 2,
      "to_period" : null,
      "start_reason" : "Substitution - On (Tactical)",
      "end_reason" : "Final Whistle"
    } ]
  }, {
    "player_id" : 80416,
    "player_name" : "Darren Sidoel",
    "player_nickname" : null,
    "jersey_number" : 6,
    "country" : {
      "id" : 160,
      "name" : "Netherlands"
    },
    "cards" : [ ],
    "positions" : [ {
      "position_id" : 24,
      "position" : "Left Center Forward",
      "from" : "00:00",
      "to" : "58:41",
      "from_period" : 1,
      "to_period" : 2,
      "start_reason" : "Starting XI",
      "end_reason" : "Substitution - Off (Tactical)"
    } ]
  }, {
    "player_id" : 124760,
    "player_name" : "Adil Khan",
    "player_nickname" : null,
    "jersey_number" : 5,
    "country" : {
      "id" : 105,
      "name" : "India"
    },
    "cards" : [ ],
    "positions" : [ {
      "position_id" : 2,
      "position" : "Right Back",
      "from" : "71:00",
      "to" : "72:21",
      "from_period" : 2,
      "to_period" : 2,
      "start_reason" : "Substitution - On (Tactical)",
      "end_reason" : "Tactical Shift"
    }, {
      "position_id" : 3,
      "position" : "Right Center Back",
      "from" : "72:21",
      "to" : null,
      "from_period" : 2,
      "to_period" : null,
      "start_reason" : "Tactical Shift",
      "end_reason" : "Final Whistle"
    } ]
  }, {
    "player_id" : 161091,
    "player_name" : "Daniel Chima Chukwu",
    "player_nickname" : null,
    "jersey_number" : 27,
    "country" : {
      "id" : 166,
      "name" : "Nigeria"
    },
    "cards" : [ ],
    "positions" : [ {
      "position_id" : 24,
      "position" : "Left Center Forward",
      "from" : "58:41",
      "to" : null,
      "from_period" : 2,
      "to_period" : null,
      "start_reason" : "Substitution - On (Tactical)",
      "end_reason" : "Final Whistle"
    } ]
  }, {
    "player_id" : 161092,
    "player_name" : "Amir Derviševič",
    "player_nickname" : null,
    "jersey_number" : 21,
    "country" : {
      "id" : 208,
      "name" : "Slovenia"
    },
    "cards" : [ ],
    "positions" : [ {
      "position_id" : 11,
      "position" : "Left Defensive Midfield",
      "from" : "00:00",
      "to" : "58:34",
      "from_period" : 1,
      "to_period" : 2,
      "start_reason" : "Starting XI",
      "end_reason" : "Substitution - Off (Tactical)"
    } ]
  }, {
    "player_id" : 161093,
    "player_name" : "Bikash Jairu",
    "player_nickname" : null,
    "jersey_number" : 23,
    "country" : {
      "id" : 105,
      "name" : "India"
    },
    "cards" : [ ],
    "positions" : [ {
      "position_id" : 16,
      "position" : "Left Midfield",
      "from" : "00:00",
      "to" : null,
      "from_period" : 1,
      "to_period" : null,
      "start_reason" : "Starting XI",
      "end_reason" : "Final Whistle"
    } ]
  }, {
    "player_id" : 161094,
    "player_name" : "Mohammed Rafique",
    "player_nickname" : null,
    "jersey_number" : 8,
    "country" : {
      "id" : 105,
      "name" : "India"
    },
    "cards" : [ ],
    "positions" : [ {
      "position_id" : 9,
      "position" : "Right Defensive Midfield",
      "from" : "00:00",
      "to" : null,
      "from_period" : 1,
      "to_period" : null,
      "start_reason" : "Starting XI",
      "end_reason" : "Final Whistle"
    } ]
  }, {
    "player_id" : 161106,
    "player_name" : "Amarjit Singh Kiyam Singh",
    "player_nickname" : null,
    "jersey_number" : 80,
    "country" : {
      "id" : 105,
      "name" : "India"
    },
    "cards" : [ ],
    "positions" : [ {
      "position_id" : 11,
      "position" : "Left Defensive Midfield",
      "from" : "58:34",
      "to" : null,
      "from_period" : 2,
      "to_period" : null,
      "start_reason" : "Substitution - On (Tactical)",
      "end_reason" : "Final Whistle"
    } ]
  }, {
    "player_id" : 161108,
    "player_name" : "Hira Mondal",
    "player_nickname" : null,
    "jersey_number" : 20,
    "country" : {
      "id" : 105,
      "name" : "India"
    },
    "cards" : [ {
      "time" : "60:51",
      "card_type" : "Yellow Card",
      "reason" : "Foul Committed",
      "period" : 2
    } ],
    "positions" : [ {
      "position_id" : 6,
      "position" : "Left Back",
      "from" : "00:00",
      "to" : null,
      "from_period" : 1,
      "to_period" : null,
      "start_reason" : "Starting XI",
      "end_reason" : "Final Whistle"
    } ]
  }, {
    "player_id" : 161110,
    "player_name" : "Lalrinliana Hnamte",
    "player_nickname" : null,
    "jersey_number" : 22,
    "country" : {
      "id" : 105,
      "name" : "India"
    },
    "cards" : [ ],
    "positions" : [ ]
  }, {
    "player_id" : 161111,
    "player_name" : "Antonio Perošević",
    "player_nickname" : null,
    "jersey_number" : 7,
    "country" : {
      "id" : 56,
      "name" : "Croatia"
    },
    "cards" : [ ],
    "positions" : [ {
      "position_id" : 22,
      "position" : "Right Center Forward",
      "from" : "00:00",
      "to" : "71:00",
      "from_period" : 1,
      "to_period" : 2,
      "start_reason" : "Starting XI",
      "end_reason" : "Substitution - Off (Off Camera)"
    } ]
  }, {
    "player_id" : 161112,
    "player_name" : "Joyner Lourenco",
    "player_nickname" : null,
    "jersey_number" : 12,
    "country" : {
      "id" : 105,
      "name" : "India"
    },
    "cards" : [ ],
    "positions" : [ {
      "position_id" : 2,
      "position" : "Right Back",
      "from" : "00:00",
      "to" : "71:00",
      "from_period" : 1,
      "to_period" : 2,
      "start_reason" : "Starting XI",
      "end_reason" : "Substitution - Off (Tactical)"
    } ]
  }, {
    "player_id" : 161113,
    "player_name" : "Daniel Gomes",
    "player_nickname" : null,
    "jersey_number" : 2,
    "country" : {
      "id" : 105,
      "name" : "India"
    },
    "cards" : [ ],
    "positions" : [ ]
  }, {
    "player_id" : 161114,
    "player_name" : "Thongkhosiem Haokip",
    "player_nickname" : null,
    "jersey_number" : 24,
    "country" : {
      "id" : 105,
      "name" : "India"
    },
    "cards" : [ ],
    "positions" : [ {
      "position_id" : 22,
      "position" : "Right Center Forward",
      "from" : "71:00",
      "to" : null,
      "from_period" : 2,
      "to_period" : null,
      "start_reason" : "Substitution - On (Off Camera)",
      "end_reason" : "Final Whistle"
    } ]
  }, {
    "player_id" : 161115,
    "player_name" : "Suvam Sen",
    "player_nickname" : null,
    "jersey_number" : 25,
    "country" : {
      "id" : 105,
      "name" : "India"
    },
    "cards" : [ ],
    "positions" : [ {
      "position_id" : 1,
      "position" : "Goalkeeper",
      "from" : "00:00",
      "to" : null,
      "from_period" : 1,
      "to_period" : null,
      "start_reason" : "Starting XI",
      "end_reason" : "Final Whistle"
    } ]
  }, {
    "player_id" : 166424,
    "player_name" : "Raju Eknath Gaikwad",
    "player_nickname" : null,
    "jersey_number" : 47,
    "country" : {
      "id" : 105,
      "name" : "India"
    },
    "cards" : [ ],
    "positions" : [ {
      "position_id" : 3,
      "position" : "Right Center Back",
      "from" : "00:00",
      "to" : "72:21",
      "from_period" : 1,
      "to_period" : 2,
      "start_reason" : "Starting XI",
      "end_reason" : "Tactical Shift"
    }, {
      "position_id" : 2,
      "position" : "Right Back",
      "from" : "72:21",
      "to" : null,
      "from_period" : 2,
      "to_period" : null,
      "start_reason" : "Tactical Shift",
      "end_reason" : "Final Whistle"
    } ]
  }, {
    "player_id" : 166425,
    "player_name" : "Naorem Mahesh Singh",
    "player_nickname" : null,
    "jersey_number" : 13,
    "country" : {
      "id" : 105,
      "name" : "India"
    },
    "cards" : [ ],
    "positions" : [ {
      "position_id" : 12,
      "position" : "Right Midfield",
      "from" : "00:00",
      "to" : null,
      "from_period" : 1,
      "to_period" : null,
      "start_reason" : "Starting XI",
      "end_reason" : "Final Whistle"
    } ]
  }, {
    "player_id" : 167381,
    "player_name" : "Sankar Roy",
    "player_nickname" : null,
    "jersey_number" : 1,
    "country" : {
      "id" : 105,
      "name" : "India"
    },
    "cards" : [ ],
    "positions" : [ ]
  } ]
} ]